event_systems/__init__.py
event_systems/common_expressions.py
event_systems/py.typed
event_systems/base/__init__.py
event_systems/base/async_protocols.py
event_systems/base/handler.py
event_systems/base/threaded_protocols.py
event_systems/instanced/__init__.py
event_systems/instanced/async_event_system.py
event_systems/instanced/threaded_event_system.py
event_systems/singleton/__init__.py
event_systems/singleton/async_event_system.py
event_systems-0.3.7.dist-info/licenses/LICENCE
event_systems-0.3.7.dist-info/METADATA
event_systems-0.3.7.dist-info/WHEEL
event_systems-0.3.7.dist-info/top_level.txt
event_systems-0.3.7.dist-info/RECORD
