Metadata-Version: 2.4
Name: event-systems
Version: 0.3.7
Summary: A collection of thread-safe event systems which components can use to subscribe and post to other components.
Author-email: sir_even@icloud.com
License: MIT
Project-URL: Homepage, https://github.com/sirEven/event-systems.git
Classifier: Programming Language :: Python :: 3
Classifier: Operating System :: OS Independent
Requires-Python: >=3.10
License-File: LICENCE
Dynamic: license-file
